{
  "nugetPackages": {
    "Microsoft.AspNetCore.SpaProxy": "6.0.0",
    "Serilog.AspNetCore": "6.1.0",
    "Microsoft.AspNetCore.Mvc.Versioning": "5.0.0",
    "Serilog.Expressions": "3.4.1",
    "MediatR": "11.1.0",
    "IdentityModel": "6.1.0-preview.1",
    "IdentityServer4.AccessTokenValidation": "3.0.1",
    "Microsoft.OpenApi": "1.5.0",
    "FluentValidation": "11.4.0",
    "Microsoft.AspNetCore.Mvc.Versioning.ApiExplorer": "5.0.0",
    "Microsoft.Extensions.DependencyInjection": "7.0.0",
    "AutoMapper": "12.0.1",
    "MailKit": "3.4.3",
    "MimeKit": "3.4.3",
    "Microsoft.EntityFrameworkCore": "7.0.2",
    "System.Linq.Dynamic.Core": "1.2.24",
    "Microsoft.Extensions.Configuration": "7.0.0",
    "Microsoft.Extensions.Configuration.Binder": "7.0.2",
    "Microsoft.EntityFrameworkCore.InMemory": "7.0.2",
    "Microsoft.EntityFrameworkCore.SqlServer": "7.0.2",
    "Microsoft.Extensions.Options.ConfigurationExtensions": "7.0.0",
    "Microsoft.Extensions.Configuration.Json": "7.0.0",
    "Swashbuckle.AspNetCore.SwaggerUI": "6.5.0",
    "Npgsql.EntityFrameworkCore.PostgreSQL": "7.0.1",
    "Npgsql.EntityFrameworkCore.PostgreSQL.Design": "2.0.0-preview1",
    "NETStandard.Library": "2.0.3",
    "Consul": "1.6.10.8",
    "Microsoft.Extensions.Hosting": "7.0.0",
    "Microsoft.AspNetCore.OpenApi": "7.0.2",
    "Ocelot": "18.0.0",
    "Ocelot.Provider.Consul": "18.0.0",
    "Ocelot.Administration": "18.0.0",
    "Swashbuckle.AspNetCore": "6.5.0",
    "Microsoft.Extensions.Logging": "7.0.0",
    "CsvHelper": "30.0.1",
    "Microsoft.AspNetCore.Identity": "2.2.0",
    "Microsoft.AspNetCore.Authentication": "2.2.0",
    "FluentValidation.DependencyInjectionExtensions": "11.4.0",
    "AutoMapper.Extensions.Microsoft.DependencyInjection": "12.0.0",
    "MediatR.Extensions.Microsoft.DependencyInjection": "11.0.0",
    "Microsoft.AspNetCore.ApiAuthorization.IdentityServer": "7.0.2",
    "Microsoft.AspNetCore.Identity.EntityFrameworkCore": "7.0.2",
    "IdentityServer4": "4.1.2",
    "Microsoft.AspNetCore.Diagnostics.EntityFrameworkCore": "7.0.2",
    "Microsoft.AspNetCore.Authentication.Cookies": "2.2.0",
    "Microsoft.AspNetCore.Authentication.Google": "7.0.2",
    "AspNetCore.HealthChecks.UI.Client": "6.0.5",
    "AspNetCore.HealthChecks.Uris": "6.0.3",
    "Polly": "7.2.3",
    "Polly.Extensions.Http": "3.0.0",
    "Serilog.Sinks.Elasticsearch": "9.0.0-beta9",
    "Serilog.Enrichers.Environment": "2.3.0-dev-00791",
    "Ocelot.Cache.CacheManager": "18.0.0",
    "Ocelot.Provider.Polly": "18.0.0",
    "LinqKit": "1.2.3",
    "Quartz": "3.6.0",
    "Microsoft.AspNetCore.Authentication.Facebook": "7.0.2",
    "Microsoft.AspNetCore.Authentication.MicrosoftAccount": "7.0.2",
    "Microsoft.Extensions.Caching.StackExchangeRedis": "8.0.0-preview.1.23112.2",
    "Microsoft.Extensions.Diagnostics.HealthChecks.EntityFrameworkCore": "7.0.3",
    "AspNetCore.HealthChecks.UI": "7.0.0-rc2.7",
    "Microsoft.AspNetCore.Mvc": "2.2.0",
    "Swashbuckle.AspNetCore.Swagger": "6.5.0",
    "Microsoft.EntityFrameworkCore.AutoHistory": "6.0.0",
    "AutoMapper.Collection.EntityFrameworkCore": "9.0.0",
    "Automapper.Collection": "9.0.0",
    "AutoMapper.Extensions.ExpressionMapping": "6.0.3",
    "AutoMapper.Collection": "9.0.0",
    "Nito.AsyncEx": "5.1.2",
    "Ben.Demystifier": "0.4.1",
    "NetEscapades.AspNetCore.SecurityHeaders": "0.18.0"
  }
}
